LICENSE
MANIFEST.in
README.rst
requirements.txt
setup.cfg
setup.py
versioneer.py
fbchat_archive_parser/__init__.py
fbchat_archive_parser/_version.py
fbchat_archive_parser/main.py
fbchat_archive_parser/name_resolver.py
fbchat_archive_parser/parser.py
fbchat_archive_parser/stats.py
fbchat_archive_parser/time.py
fbchat_archive_parser/utils.py
fbchat_archive_parser.egg-info/PKG-INFO
fbchat_archive_parser.egg-info/SOURCES.txt
fbchat_archive_parser.egg-info/dependency_links.txt
fbchat_archive_parser.egg-info/entry_points.txt
fbchat_archive_parser.egg-info/requires.txt
fbchat_archive_parser.egg-info/top_level.txt
fbchat_archive_parser/writers/__init__.py
fbchat_archive_parser/writers/csv.py
fbchat_archive_parser/writers/dict.py
fbchat_archive_parser/writers/json.py
fbchat_archive_parser/writers/pretty_json.py
fbchat_archive_parser/writers/text.py
fbchat_archive_parser/writers/writer.py
fbchat_archive_parser/writers/yaml.py