Metadata-Version: 1.1
Name: fbchat-archive-parser
Version: 2.0.0
Summary: A library/command line utility for parsing Facebook chat history
Home-page: https://github.com/ownaginatious/fbchat-archive-parser
Author: Dillon Dixon
Author-email: dillondixon@gmail.com
License: MIT
Keywords: facebook,chat,messenger,history
Platform: UNKNOWN
Classifier: Environment :: Console
Classifier: License :: OSI Approved :: MIT License
Classifier: Programming Language :: Python :: 2.7
Classifier: Programming Language :: Python :: 3.5
Classifier: Programming Language :: Python :: 3.6
